{
  "_class": "group",
  "booleanOperation": 0,
  "do_objectID": "5D1CC413-351F-43DD-BBD3-07F9E7F7E28C",
  "exportOptions": {
    "_class": "exportOptions",
    "do_objectID": "060D4EFF-FB94-4AF5-8983-8B1F5D21F937",
    "exportFormats": [
    ],
    "includedLayerIds": [
    ],
    "layerOptions": 0,
    "shouldTrim": false
  },
  "frame": {
    "_class": "rect",
    "constrainProportions": false,
    "do_objectID": "AAD52C56-3423-465E-A210-2B07A932491E",
    "height": 30,
    "width": 38,
    "x": 0,
    "y": 0.9615384615384528
  },
  "hasClickThrough": false,
  "isFixedToViewport": false,
  "isFlippedHorizontal": true,
  "isFlippedVertical": false,
  "isLocked": false,
  "isVisible": true,
  "layerListExpandedType": 2,
  "layers": [
    {
      "class": "shapeGroup",
      "id": "1DBD0DD7-C4BC-4522-9212-0B2E76D2D48A"
    }
  ],
  "name": "g3596",
  "nameIsFixed": false,
  "resizingConstraint": 63,
  "resizingType": 0,
  "rotation": 180,
  "shouldBreakMaskChain": false,
  "style": {
    "_class": "style",
    "do_objectID": "2F5B7FF4-9066-45E0-9635-17D048EBDD0F",
    "endMarkerType": 0,
    "fills": [
      {
        "_class": "fill",
        "color": {
          "_class": "color",
          "alpha": 1,
          "blue": 0,
          "green": 0,
          "red": 0
        },
        "fillType": 0,
        "isEnabled": true,
        "noiseIndex": 0,
        "noiseIntensity": 0,
        "patternFillType": 1,
        "patternTileScale": 1
      }
    ],
    "miterLimit": 10,
    "startMarkerType": 0,
    "windingRule": 1
  },
  "userInfo": {
    "com.animaapp.stc-sketch-plugin": {
      "kModelPropertiesKey": {
      }
    }
  }
}