{
  "_class": "shapeGroup",
  "booleanOperation": 0,
  "clippingMaskMode": 0,
  "do_objectID": "AF5F11F4-102D-49E1-AFA5-CE50419C3B28",
  "exportOptions": {
    "_class": "exportOptions",
    "do_objectID": "7BCFB6A6-DBFA-4BAA-B1AA-64003AE18D36",
    "exportFormats": [
    ],
    "includedLayerIds": [
    ],
    "layerOptions": 0,
    "shouldTrim": false
  },
  "frame": {
    "_class": "rect",
    "constrainProportions": false,
    "do_objectID": "D0B85E82-4930-42E8-96EE-9B3545E16608",
    "height": 13.10938775510205,
    "width": 5.76979591836735,
    "x": 10.08857142857143,
    "y": 0.08734693877550877
  },
  "hasClickThrough": false,
  "hasClippingMask": false,
  "isFixedToViewport": false,
  "isFlippedHorizontal": false,
  "isFlippedVertical": false,
  "isLocked": false,
  "isVisible": true,
  "layerListExpandedType": 1,
  "layers": [
    {
      "class": "shapePath",
      "id": "5E55FF6A-C74F-4E9F-AA71-4E9553A9F1AC"
    }
  ],
  "name": "Shape",
  "nameIsFixed": false,
  "resizingConstraint": 63,
  "resizingType": 0,
  "rotation": 0,
  "shouldBreakMaskChain": false,
  "style": {
    "_class": "style",
    "blur": {
      "_class": "blur",
      "center": "{0.5, 0.5}",
      "do_objectID": "46104DDF-9D00-40D0-A446-D56CAB2D0C38",
      "isEnabled": false,
      "motionAngle": 0,
      "radius": 1,
      "type": 0
    },
    "do_objectID": "5C060B2A-F291-4B88-944D-FD7DCF419198",
    "endMarkerType": 0,
    "fills": [
      {
        "_class": "fill",
        "color": {
          "_class": "color",
          "alpha": 1,
          "blue": 1,
          "green": 1,
          "red": 1
        },
        "fillType": 0,
        "isEnabled": true,
        "noiseIndex": 0,
        "noiseIntensity": 0,
        "patternFillType": 1,
        "patternTileScale": 1
      }
    ],
    "miterLimit": 10,
    "startMarkerType": 0,
    "windingRule": 0
  },
  "userInfo": {
    "com.animaapp.stc-sketch-plugin": {
      "kModelPropertiesKey": {
      }
    }
  },
  "windingRule": 0
}