{
  "_class": "rectangle",
  "booleanOperation": -1,
  "do_objectID": "5030DBE2-2449-45F5-A5E6-76818017D6AB",
  "edited": false,
  "exportOptions": {
    "_class": "exportOptions",
    "do_objectID": "B52BF02B-FA43-4D2E-8526-D39131363FA1",
    "exportFormats": [
    ],
    "includedLayerIds": [
    ],
    "layerOptions": 0,
    "shouldTrim": false
  },
  "fixedRadius": 0,
  "frame": {
    "_class": "rect",
    "constrainProportions": false,
    "do_objectID": "62ECB4F9-E1C3-4DED-A8DA-79A3C0D72CA4",
    "height": 5,
    "width": 275.0000000000001,
    "x": 0,
    "y": 0
  },
  "hasConvertedToNewRoundCorners": true,
  "isClosed": true,
  "isFlippedHorizontal": false,
  "isFlippedVertical": false,
  "isLocked": false,
  "isVisible": true,
  "layerListExpandedType": 0,
  "name": "Path",
  "nameIsFixed": false,
  "path": {
    "_class": "path",
    "isClosed": true,
    "pointRadiusBehaviour": 0,
    "points": [
      {
        "_class": "curvePoint",
        "cornerRadius": 0,
        "curveFrom": "{0, 0}",
        "curveMode": 1,
        "curveTo": "{0, 0}",
        "hasCurveFrom": false,
        "hasCurveTo": false,
        "point": "{0, 0}"
      },
      {
        "_class": "curvePoint",
        "cornerRadius": 0,
        "curveFrom": "{1, 0}",
        "curveMode": 1,
        "curveTo": "{1, 0}",
        "hasCurveFrom": false,
        "hasCurveTo": false,
        "point": "{1, 0}"
      },
      {
        "_class": "curvePoint",
        "cornerRadius": 0,
        "curveFrom": "{1, 1}",
        "curveMode": 1,
        "curveTo": "{1, 1}",
        "hasCurveFrom": false,
        "hasCurveTo": false,
        "point": "{1, 1}"
      },
      {
        "_class": "curvePoint",
        "cornerRadius": 0,
        "curveFrom": "{0, 1}",
        "curveMode": 1,
        "curveTo": "{0, 1}",
        "hasCurveFrom": false,
        "hasCurveTo": false,
        "point": "{0, 1}"
      }
    ]
  },
  "pointRadiusBehaviour": 0,
  "points": [
    {
      "_class": "curvePoint",
      "cornerRadius": 0,
      "curveFrom": "{0, 0}",
      "curveMode": 1,
      "curveTo": "{0, 0}",
      "hasCurveFrom": false,
      "hasCurveTo": false,
      "point": "{0, 0}"
    },
    {
      "_class": "curvePoint",
      "cornerRadius": 0,
      "curveFrom": "{1, 0}",
      "curveMode": 1,
      "curveTo": "{1, 0}",
      "hasCurveFrom": false,
      "hasCurveTo": false,
      "point": "{1, 0}"
    },
    {
      "_class": "curvePoint",
      "cornerRadius": 0,
      "curveFrom": "{1, 1}",
      "curveMode": 1,
      "curveTo": "{1, 1}",
      "hasCurveFrom": false,
      "hasCurveTo": false,
      "point": "{1, 1}"
    },
    {
      "_class": "curvePoint",
      "cornerRadius": 0,
      "curveFrom": "{0, 1}",
      "curveMode": 1,
      "curveTo": "{0, 1}",
      "hasCurveFrom": false,
      "hasCurveTo": false,
      "point": "{0, 1}"
    }
  ],
  "resizingConstraint": 63,
  "resizingType": 0,
  "rotation": 0,
  "shouldBreakMaskChain": false
}