{
  "_class": "symbolInstance",
  "booleanOperation": 0,
  "do_objectID": "6CF94A1E-1F2D-4BBF-98D3-FF8F1F9E009D",
  "exportOptions": {
    "_class": "exportOptions",
    "do_objectID": "FBEA500F-DA2C-461D-BC24-A4C27AC45AFB",
    "exportFormats": [
    ],
    "includedLayerIds": [
    ],
    "layerOptions": 0,
    "shouldTrim": false
  },
  "frame": {
    "_class": "rect",
    "constrainProportions": false,
    "do_objectID": "2D413F48-2924-435F-94E3-B20494264D9A",
    "height": 27,
    "width": 299,
    "x": 411,
    "y": 172
  },
  "horizontalSpacing": 0,
  "isFixedToViewport": false,
  "isFlippedHorizontal": false,
  "isFlippedVertical": false,
  "isLocked": false,
  "isVisible": true,
  "layerListExpandedType": 0,
  "name": "Analytics / Team / Time Selection",
  "nameIsFixed": false,
  "overrideValues": [
  ],
  "resizingConstraint": 47,
  "resizingType": 0,
  "rotation": 0,
  "scale": 1,
  "shouldBreakMaskChain": false,
  "style": {
    "_class": "style",
    "do_objectID": "D3CB30C9-9891-4E3E-8F67-7C9E828B0FEF",
    "endMarkerType": 0,
    "miterLimit": 10,
    "startMarkerType": 0,
    "windingRule": 1
  },
  "symbolID": "A7458223-397E-4C18-BDEB-4BB548D99C36",
  "verticalSpacing": 0
}