{
  "_class": "shapeGroup",
  "clippingMaskMode": 0,
  "do_objectID": "EECC3221-F87E-4A8E-8F00-1F823CFE4439",
  "exportOptions": {
    "_class": "exportOptions",
    "do_objectID": "FD45C2A7-F3EE-4F2B-AE68-E1859811AE59",
    "exportFormats": [
    ],
    "includedLayerIds": [
    ],
    "layerOptions": 0,
    "shouldTrim": false
  },
  "frame": {
    "_class": "rect",
    "constrainProportions": false,
    "do_objectID": "A1614294-C298-4C13-BA9B-16D07F20775C",
    "height": 1,
    "width": 5,
    "x": 18,
    "y": 0
  },
  "hasClickThrough": false,
  "hasClippingMask": false,
  "isFlippedHorizontal": false,
  "isFlippedVertical": false,
  "isLocked": false,
  "isVisible": true,
  "layerListExpandedType": 1,
  "layers": [
    {
      "class": "rectangle",
      "id": "21DB8E99-1C5E-448B-8A71-B20E27FFC460"
    }
  ],
  "name": "ruler-start",
  "nameIsFixed": false,
  "resizingConstraint": 63,
  "resizingType": 0,
  "rotation": 0,
  "shouldBreakMaskChain": false,
  "style": {
    "_class": "style",
    "do_objectID": "68ED7CD1-EC0C-48F2-A9E3-A4D8581DADAA",
    "endDecorationType": 0,
    "fills": [
      {
        "_class": "fill",
        "color": {
          "_class": "color",
          "alpha": 1,
          "blue": 0,
          "green": 0.333333,
          "red": 1
        },
        "fillType": 0,
        "isEnabled": true,
        "noiseIndex": 0,
        "noiseIntensity": 0,
        "patternFillType": 1,
        "patternTileScale": 1
      }
    ],
    "miterLimit": 10,
    "sharedObjectID": "06A113DE-CBD3-4BC7-8D6F-759C6F589D79",
    "startDecorationType": 0
  },
  "windingRule": 1
}