{
  "_class": "group",
  "booleanOperation": 0,
  "do_objectID": "DC45979A-20C2-4D92-8676-72CFA50956E1",
  "exportOptions": {
    "_class": "exportOptions",
    "do_objectID": "B1D60DA4-D469-4C54-A9B0-0EE02A340B82",
    "exportFormats": [
    ],
    "includedLayerIds": [
    ],
    "layerOptions": 0,
    "shouldTrim": false
  },
  "frame": {
    "_class": "rect",
    "constrainProportions": false,
    "do_objectID": "18EF6A0D-395C-459E-8B44-20DA2372170A",
    "height": 64,
    "width": 64,
    "x": 28,
    "y": 17
  },
  "hasClickThrough": false,
  "isFixedToViewport": false,
  "isFlippedHorizontal": false,
  "isFlippedVertical": false,
  "isLocked": false,
  "isVisible": true,
  "layerListExpandedType": 2,
  "layers": [
    {
      "class": "shapeGroup",
      "id": "E11E6298-A8D7-41F7-AD81-39C901D5787C"
    }
  ],
  "name": "image",
  "nameIsFixed": false,
  "resizingConstraint": 63,
  "resizingType": 0,
  "rotation": 0,
  "shouldBreakMaskChain": false,
  "style": {
    "_class": "style",
    "contextSettings": {
      "_class": "graphicsContextSettings",
      "blendMode": 0,
      "do_objectID": "070203B2-FABC-4B79-8276-134A23CD44D7",
      "opacity": 0.9008278917910447
    },
    "do_objectID": "FDDCDDF7-B08C-4496-8D86-31D7FB754C1B",
    "endMarkerType": 0,
    "miterLimit": 10,
    "startMarkerType": 0,
    "windingRule": 1
  },
  "userInfo": {
    "com.animaapp.stc-sketch-plugin": {
      "kModelPropertiesKey": {
      }
    }
  }
}