{
  "_class": "shapeGroup",
  "booleanOperation": 0,
  "clippingMaskMode": 0,
  "do_objectID": "7D955A5E-13B4-4759-B0F1-1087E98B41E3",
  "exportOptions": {
    "_class": "exportOptions",
    "do_objectID": "D53DCCD8-32CC-4304-8A2A-44682F61805E",
    "exportFormats": [
    ],
    "includedLayerIds": [
    ],
    "layerOptions": 0,
    "shouldTrim": false
  },
  "frame": {
    "_class": "rect",
    "constrainProportions": false,
    "do_objectID": "88AC806A-51A1-4D5C-AB0E-130BBE35B1D9",
    "height": 5,
    "width": 1,
    "x": 63,
    "y": 8
  },
  "hasClickThrough": false,
  "hasClippingMask": false,
  "isFixedToViewport": false,
  "isFlippedHorizontal": false,
  "isFlippedVertical": false,
  "isLocked": false,
  "isVisible": true,
  "layerListExpandedType": 1,
  "layers": [
    {
      "class": "rectangle",
      "id": "EAF536EC-A282-49E4-ACFB-9587CD71791A"
    }
  ],
  "name": "ruler-end",
  "nameIsFixed": false,
  "resizingConstraint": 63,
  "resizingType": 0,
  "rotation": 0,
  "shouldBreakMaskChain": false,
  "style": {
    "_class": "style",
    "do_objectID": "015B99F4-1280-4A2F-A50C-ECEEA37C77C3",
    "endMarkerType": 0,
    "fills": [
      {
        "_class": "fill",
        "color": {
          "_class": "color",
          "alpha": 1,
          "blue": 0,
          "green": 0.333333,
          "red": 1
        },
        "fillType": 0,
        "isEnabled": true,
        "noiseIndex": 0,
        "noiseIntensity": 0,
        "patternFillType": 1,
        "patternTileScale": 1
      }
    ],
    "miterLimit": 10,
    "sharedObjectID": "06A113DE-CBD3-4BC7-8D6F-759C6F589D79",
    "startMarkerType": 0,
    "windingRule": 1
  },
  "windingRule": 1
}