{
  "_class": "text",
  "attributedString": {
    "_class": "attributedString",
    "attributes": [
      {
        "_class": "stringAttribute",
        "attributes": {
          "MSAttributedStringColorAttribute": {
            "_class": "color",
            "alpha": 1,
            "blue": 0.06666666667,
            "green": 0.06666666667,
            "red": 0.06666666667
          },
          "MSAttributedStringFontAttribute": {
            "_class": "fontDescriptor",
            "attributes": {
              "name": "Lato-Bold",
              "size": 18
            }
          },
          "paragraphStyle": {
            "_class": "paragraphStyle",
            "alignment": 2,
            "allowsDefaultTighteningForTruncation": 0,
            "maximumLineHeight": 24,
            "minimumLineHeight": 24
          }
        },
        "length": 6,
        "location": 0
      }
    ],
    "string": "15 Mar"
  },
  "automaticallyDrawOnUnderlyingPath": false,
  "booleanOperation": 0,
  "do_objectID": "1A16DD60-EF0F-4409-8DF6-7368DEABA9EB",
  "dontSynchroniseWithSymbol": false,
  "exportOptions": {
    "_class": "exportOptions",
    "do_objectID": "A3518700-3B27-474B-92E2-728622C013D1",
    "exportFormats": [
    ],
    "includedLayerIds": [
    ],
    "layerOptions": 0,
    "shouldTrim": false
  },
  "frame": {
    "_class": "rect",
    "constrainProportions": false,
    "do_objectID": "5E6ACA05-2ED0-41A0-8EB7-F314E2F189F0",
    "height": 34.1937052309335,
    "width": 84.88746011757036,
    "x": 0.4437300587850359,
    "y": 0
  },
  "glyphBounds": "{{14, 4}, {58, 15}}",
  "isFixedToViewport": false,
  "isFlippedHorizontal": false,
  "isFlippedVertical": false,
  "isLocked": false,
  "isVisible": true,
  "layerListExpandedType": 0,
  "lineSpacingBehaviour": 1,
  "name": "15 Mar",
  "nameIsFixed": false,
  "resizingConstraint": 63,
  "resizingType": 0,
  "rotation": 0,
  "shouldBreakMaskChain": false,
  "style": {
    "_class": "style",
    "do_objectID": "F5ECBEBE-1D7B-420A-A6D7-3797202FD56A",
    "endMarkerType": 0,
    "miterLimit": 10,
    "sharedObjectID": "73844FFD-F497-43FE-95A0-DDA708D7EA91",
    "startMarkerType": 0,
    "textStyle": {
      "_class": "textStyle",
      "encodedAttributes": {
        "MSAttributedStringColorAttribute": {
          "_class": "color",
          "alpha": 1,
          "blue": 0.06666666667,
          "green": 0.06666666667,
          "red": 0.06666666667
        },
        "MSAttributedStringFontAttribute": {
          "_class": "fontDescriptor",
          "attributes": {
            "name": "Lato-Bold",
            "size": 18
          }
        },
        "paragraphStyle": {
          "_class": "paragraphStyle",
          "alignment": 2,
          "allowsDefaultTighteningForTruncation": 0,
          "maximumLineHeight": 24,
          "minimumLineHeight": 24
        }
      },
      "verticalAlignment": 0
    },
    "windingRule": 1
  },
  "textBehaviour": 2,
  "userInfo": {
    "com.animaapp.stc-sketch-plugin": {
      "kModelPropertiesKey": {
        "isAutoWidth": 0
      }
    }
  }
}