{
  "_class": "shapeGroup",
  "booleanOperation": 0,
  "clippingMaskMode": 0,
  "do_objectID": "57FA2FD1-9742-41BA-8A72-33793B43C887",
  "exportOptions": {
    "_class": "exportOptions",
    "do_objectID": "BFA9928D-EE44-4271-B6A9-0A111891CCFF",
    "exportFormats": [
    ],
    "includedLayerIds": [
    ],
    "layerOptions": 0,
    "shouldTrim": false
  },
  "frame": {
    "_class": "rect",
    "constrainProportions": false,
    "do_objectID": "E6E616AE-B862-4ACD-B13C-842D7A1DE030",
    "height": 28.46600033798737,
    "width": 32,
    "x": 429.4640972609818,
    "y": 194.4660003379869
  },
  "hasClickThrough": false,
  "hasClippingMask": false,
  "isFixedToViewport": false,
  "isFlippedHorizontal": false,
  "isFlippedVertical": false,
  "isLocked": false,
  "isVisible": true,
  "layerListExpandedType": 1,
  "layers": [
    {
      "class": "rectangle",
      "id": "444C34B4-439E-40E7-A7A2-BC40D89160D3"
    }
  ],
  "name": "Rectangle Copy 5",
  "nameIsFixed": false,
  "resizingConstraint": 63,
  "resizingType": 0,
  "rotation": 0,
  "shouldBreakMaskChain": false,
  "style": {
    "_class": "style",
    "borderOptions": {
      "_class": "borderOptions",
      "dashPattern": [
        8
      ],
      "do_objectID": "817B415B-A801-442B-AD98-2B60E630E66F",
      "isEnabled": false,
      "lineCapStyle": 0,
      "lineJoinStyle": 0
    },
    "borders": [
      {
        "_class": "border",
        "color": {
          "_class": "color",
          "alpha": 1,
          "blue": 1,
          "green": 0.4980392156862746,
          "red": 0.4862745098039216
        },
        "fillType": 0,
        "isEnabled": false,
        "position": 1,
        "thickness": 4
      }
    ],
    "do_objectID": "7DB80002-DBAC-465D-A15A-6783FEC6FBDD",
    "endMarkerType": 0,
    "fills": [
      {
        "_class": "fill",
        "color": {
          "_class": "color",
          "alpha": 1,
          "blue": 0.8765146683673469,
          "green": 0.8005344648826727,
          "red": 0.3868644681327787
        },
        "fillType": 0,
        "isEnabled": true,
        "noiseIndex": 0,
        "noiseIntensity": 0,
        "patternFillType": 1,
        "patternTileScale": 1
      }
    ],
    "miterLimit": 10,
    "startMarkerType": 0,
    "windingRule": 1
  },
  "userInfo": {
    "com.animaapp.stc-sketch-plugin": {
      "kModelPropertiesKey": {
      }
    }
  },
  "windingRule": 1
}